[
  {
    "full_name": "WorldHealthOrganization/open-source-communication-channel",
    "stargazers_count": 72,
    "open_issues_count": 9,
    "forks_count": 5
  },
  {
    "full_name": "wagtail/wagtail",
    "stargazers_count": 14765,
    "open_issues_count": 978,
    "forks_count": 3197
  },
  {
    "full_name": "google/across",
    "stargazers_count": 14,
    "open_issues_count": 4,
    "forks_count": 8
  },
  {
    "full_name": "malgamves/CommunityWriterPrograms",
    "stargazers_count": 3202,
    "open_issues_count": 11,
    "forks_count": 557
  },
  {
    "full_name": "github/maintainermonth",
    "stargazers_count": 168,
    "open_issues_count": 4,
    "forks_count": 39
  },
  {
    "full_name": "todogroup/ospo-career-path",
    "stargazers_count": 140,
    "open_issues_count": 13,
    "forks_count": 49
  },
  {
    "full_name": "AllInOpenSource/All-In",
    "stargazers_count": 81,
    "open_issues_count": 4,
    "forks_count": 12
  },
  {
    "full_name": "shikha-16/Women-in-Technology",
    "stargazers_count": 596,
    "open_issues_count": 12,
    "forks_count": 142
  },
  {
    "full_name": "LuluNwenyi/Pomodoro-Timer",
    "stargazers_count": 5,
    "open_issues_count": 0,
    "forks_count": 1
  },
  {
    "full_name": "igorbarinov/awesome-data-engineering",
    "stargazers_count": 5045,
    "open_issues_count": 52,
    "forks_count": 976
  },
  {
    "full_name": "octokatherine/readme.so",
    "stargazers_count": 3421,
    "open_issues_count": 29,
    "forks_count": 265
  },
  {
    "full_name": "kofoworola/tunnelify",
    "stargazers_count": 32,
    "open_issues_count": 0,
    "forks_count": 6
  },
  {
    "full_name": "curiouslearning/CuriousReaderRCC",
    "stargazers_count": 3,
    "open_issues_count": 0,
    "forks_count": 3
  },
  {
    "full_name": "django-stars/backend-skeleton",
    "stargazers_count": 94,
    "open_issues_count": 14,
    "forks_count": 35
  },
  {
    "full_name": "GorvGoyl/Clone-Wars",
    "stargazers_count": 24321,
    "open_issues_count": 23,
    "forks_count": 2108
  },
  {
    "full_name": "wazuh/wazuh-qa",
    "stargazers_count": 25,
    "open_issues_count": 448,
    "forks_count": 17
  },
  {
    "full_name": "FranckNdame/swiftui.builds",
    "stargazers_count": 569,
    "open_issues_count": 1,
    "forks_count": 71
  },
  {
    "full_name": "stark-contrast/stark-sketch-plugin",
    "stargazers_count": 46,
    "open_issues_count": 0,
    "forks_count": 5
  },
  {
    "full_name": "stark-contrast/blog",
    "stargazers_count": 7,
    "open_issues_count": 0,
    "forks_count": 0
  },
  {
    "full_name": "samjulien/samjulien-com",
    "stargazers_count": 7,
    "open_issues_count": 35,
    "forks_count": 1
  },
  {
    "full_name": "AnandChowdhary/bookshelf-action",
    "stargazers_count": 56,
    "open_issues_count": 9,
    "forks_count": 8
  },
  {
    "full_name": "layer5io/getnighthawk",
    "stargazers_count": 87,
    "open_issues_count": 17,
    "forks_count": 85
  },
  {
    "full_name": "Youngestdev/buycoins-python",
    "stargazers_count": 45,
    "open_issues_count": 0,
    "forks_count": 4
  },
  {
    "full_name": "devshelpdevs/DevsHelpDevs",
    "stargazers_count": 125,
    "open_issues_count": 0,
    "forks_count": 6
  },
  {
    "full_name": "Hashnode/support",
    "stargazers_count": 45,
    "open_issues_count": 12,
    "forks_count": 51
  },
  {
    "full_name": "alphacentauri82/scoutx",
    "stargazers_count": 33,
    "open_issues_count": 7,
    "forks_count": 10
  },
  {
    "full_name": "avelino/awesome-go",
    "stargazers_count": 101633,
    "open_issues_count": 144,
    "forks_count": 10956
  },
  {
    "full_name": "zenika-open-source/awesome-remote-work",
    "stargazers_count": 384,
    "open_issues_count": 6,
    "forks_count": 58
  },
  {
    "full_name": "bdougie/awesome-black-developers",
    "stargazers_count": 225,
    "open_issues_count": 1,
    "forks_count": 21
  },
  {
    "full_name": "chaoss/wg-dei",
    "stargazers_count": 74,
    "open_issues_count": 10,
    "forks_count": 54
  }
]